idem_windows/conf.py
idem_windows/version.py
idem_windows/exec/cmdmod.py
idem_windows/exec/contracts/cmdmod.py
idem_windows/exec/windows/init.py
idem_windows/exec/windows/reg.py
idem_windows/exec/windows/user.py
idem_windows/exec/windows/wmi.py
idem_windows/exec/windows/wmic.py
idem_windows/grains/windows/init.py
idem_windows/grains/windows/uname.py
idem_windows/grains/windows/hw/bios.py
idem_windows/grains/windows/hw/cpu.py
idem_windows/grains/windows/hw/disks.py
idem_windows/grains/windows/hw/gpu.py
idem_windows/grains/windows/hw/mem.py
idem_windows/grains/windows/hw/motherboard.py
idem_windows/grains/windows/hw/platform.py
idem_windows/grains/windows/hw/virtualization.py
idem_windows/grains/windows/net/dns.py
idem_windows/grains/windows/net/domain.py
idem_windows/grains/windows/net/fqdn.py
idem_windows/grains/windows/net/interfaces.py
idem_windows/grains/windows/os/info.py
idem_windows/grains/windows/os/timezone.py
idem_windows/grains/windows/proc/pid.py
idem_windows/grains/windows/proc/user.py
idem_windows/grains/windows/system/features.py
idem_windows/grains/windows/system/locale.py
idem_windows/grains/windows/system/shell.py
idem_windows/states/cmdmod.py
idem_windows/states/contracts/cmdmod.py
idem_windows/states/windows/init.py
idem_windows-5.3.dist-info/METADATA
idem_windows-5.3.dist-info/WHEEL
idem_windows-5.3.dist-info/top_level.txt
idem_windows-5.3.dist-info/RECORD
