Metadata-Version: 2.1
Name: idem-windows
Version: 5.3
Summary: Vertical app merge components for idem and grains to support windows
Home-page: https://github.com/saltstack-community/pop/idem-windows
Author: Tyler Johnson
Author-email: tjohnson@saltstack.com
License: UNKNOWN
Platform: UNKNOWN
Classifier: Operating System :: Microsoft
Classifier: Programming Language :: Python
Classifier: Programming Language :: Python :: 3.6
Classifier: Programming Language :: Python :: 3.7
Classifier: Programming Language :: Python :: 3.8
Classifier: Development Status :: 5 - Production/Stable
Requires-Python: >=3.6
Requires-Dist: dnspython (>=1.14.0)
Requires-Dist: grains-universal (>=2.1)
Requires-Dist: grains-virt (>=3)
Requires-Dist: idem (>=7.4)
Requires-Dist: pywin32 (>=223) ; sys_platform == "win32"
Requires-Dist: wmi (>=1.4.8) ; sys_platform == "win32"
